deterministic_docx_export/__init__.py
deterministic_docx_export/models/__init__.py
deterministic_docx_export/renderers/__init__.py
deterministic_docx_export/services/__init__.py
docx_template_export/__init__.py
docx_template_export/models/__init__.py
docx_template_export/models/export_config.py
docx_template_export/models/export_models.py
docx_template_export/models/export_summary.py
docx_template_export/models/markdown_tree.py
docx_template_export/renderers/__init__.py
docx_template_export/renderers/tree_renderer.py
docx_template_export/services/__init__.py
docx_template_export/services/output_path.py
docx_template_export/services/word_export_service.py
docx_template_export-0.3.1.dist-info/licenses/LICENSE
docx_template_export-0.3.1.dist-info/licenses/NOTICE
docx_template_export-0.3.1.dist-info/METADATA
docx_template_export-0.3.1.dist-info/WHEEL
docx_template_export-0.3.1.dist-info/top_level.txt
docx_template_export-0.3.1.dist-info/RECORD
