Metadata-Version: 2.4
Name: docx-template-export
Version: 0.3.1
Summary: A deterministic library for exporting markdown content to Word (.docx) templates
Home-page: https://github.com/asaeed9/deterministic-docx-export
Author: Ahsan Saeed
Keywords: docx word markdown export template deterministic
Classifier: Development Status :: 3 - Alpha
Classifier: Intended Audience :: Developers
Classifier: License :: OSI Approved :: Apache Software License
Classifier: Programming Language :: Python :: 3
Classifier: Programming Language :: Python :: 3.8
Classifier: Programming Language :: Python :: 3.9
Classifier: Programming Language :: Python :: 3.10
Classifier: Programming Language :: Python :: 3.11
Classifier: Topic :: Office/Business :: Office Suites
Classifier: Topic :: Text Processing :: Markup
Requires-Python: >=3.8
License-File: LICENSE
License-File: NOTICE
Requires-Dist: pydantic>=2.0.0
Requires-Dist: python-docx>=1.1.0
Requires-Dist: markdown-it-py>=3.0.0
Dynamic: author
Dynamic: classifier
Dynamic: description
Dynamic: description-content-type
Dynamic: home-page
Dynamic: keywords
Dynamic: license-file
Dynamic: requires-dist
Dynamic: requires-python
Dynamic: summary
